README.rst
setup.cfg
setup.py
netmem/__init__.py
netmem/__version__.py
netmem/_compat.py
netmem/bindable_variable.py
netmem/connector.py
netmem/logging_connector.py
netmem/network_memory.py
netmem/pushbullet_connector.py
netmem/udp_connector.py
netmem/websocket_connector.py
netmem/websocket_server.py
netmem.egg-info/PKG-INFO
netmem.egg-info/SOURCES.txt
netmem.egg-info/dependency_links.txt
netmem.egg-info/requires.txt
netmem.egg-info/top_level.txt