Metadata-Version: 1.1
Name: netmem
Version: 0.2.4
Summary: A network-synchronized dictionary.
Home-page: https://github.com/rharder/netmem
Author: Robert Harder
Author-email: rob@iharder.net
License: Public Domain
Download-URL: https://github.com/rharder/netmem/tarball/0.2.4
Keywords: network,memory,synchronize
Platform: UNKNOWN
Classifier: Development Status :: 4 - Beta
Classifier: Intended Audience :: Developers
Classifier: Programming Language :: Python
Classifier: Natural Language :: English
Classifier: License :: Public Domain
Classifier: Programming Language :: Python :: 3
Classifier: Programming Language :: Python :: 3.5
Classifier: Programming Language :: Python :: 3.6
Classifier: Topic :: Software Development :: Libraries :: Python Modules
Classifier: Topic :: Utilities
